dashare/__init__.py
dashare/cli.py
dashare/dashare_config.yaml
dashare/client/__init__.py
dashare/client/api.py
dashare/client/cons.py
dashare/service/__init__.py
dashare/service/cons.py
dashare/service/dbconnection.py
dashare/service/main_router.py
dashare/service/meteorological_router.py
dashare/service/user_router.py
dashare/service/wind_turbine_router.py
dashare/test/test_bug.py
dashare/test/test_dataapi.py
dashare/test/test_dbconn.py
dashare/test/test_md5.py
dashare/test/test_metadb.py
dashare/test/test_setup.py
dashare/test/test_token.py
dashare/test/test_token_tool.py
dashare/test/test_trafic_tool.py
dashare/test/test_view_df.ipynb
dashare/util/__init__.py
dashare/util/cons.py
dashare/util/info_tool.py
dashare/util/request_tool.py
dashare/util/token_tool.py
dashare/util/trafic_tool.py
shihua_dashare-0.1.dist-info/LICENSE
shihua_dashare-0.1.dist-info/METADATA
shihua_dashare-0.1.dist-info/WHEEL
shihua_dashare-0.1.dist-info/entry_points.txt
shihua_dashare-0.1.dist-info/top_level.txt
shihua_dashare-0.1.dist-info/RECORD
