Metadata-Version: 2.1
Name: shihua-dashare
Version: 0.1
Summary: DaShare is a dataapi python sdk with client and service
Home-page: https://github.com/redblue0216/DaShare
Author: shihua
Author-email: 15021408795@163.com
License: MIT
Platform: UNKNOWN
Requires-Python: >=3.9.12
License-File: LICENSE
